scrapernhl/__init__.py
scrapernhl/scraper.py
scrapernhl/models/xgboost_xG_features1.pkl
scrapernhl/models/xgboost_xG_model1.json
scrapernhl-0.1.3.dist-info/METADATA
scrapernhl-0.1.3.dist-info/WHEEL
scrapernhl-0.1.3.dist-info/top_level.txt
scrapernhl-0.1.3.dist-info/RECORD
