Metadata-Version: 2.4
Name: scrapernhl
Version: 0.1.3
Summary: Scraper for NHL data
Author-email: Max Tixador <maxtixador@gmail.com>
License: MIT
Requires-Python: >=3.12
Requires-Dist: beautifulsoup4>=4.14.3
Requires-Dist: joblib>=1.5.3
Requires-Dist: numpy>=2.3.5
Requires-Dist: pandas>=2.3.3
Requires-Dist: polars>=1.36.1
Requires-Dist: requests>=2.32.5
Requires-Dist: selectolax>=0.4.6
Requires-Dist: urllib3>=2.6.2
Requires-Dist: xgboost>=3.1.2
